[{"x": 0.485, "y": 0.947, "value": 1}, {"x": 0.489, "y": 0.961, "value": 1}, {"x": 0.491, "y": 0.917, "value": 1}, {"x": 0.492, "y": 0.906, "value": 1}, {"x": 0.506, "y": 0.9, "value": 1}, {"x": 0.514, "y": 0.927, "value": 1}, {"x": 0.517, "y": 0.889, "value": 1}, {"x": 0.521, "y": 0.808, "value": 1}, {"x": 0.521, "y": 0.877, "value": 1}, {"x": 0.521, "y": 0.891, "value": 1}, {"x": 0.521, "y": 0.883, "value": 1}, {"x": 0.521, "y": 0.9, "value": 1}, {"x": 0.526, "y": 0.874, "value": 1}, {"x": 0.527, "y": 0.874, "value": 1}, {"x": 0.528, "y": 0.93, "value": 1}, {"x": 0.529, "y": 0.813, "value": 1}, {"x": 0.531, "y": 0.803, "value": 1}, {"x": 0.534, "y": 0.853, "value": 1}, {"x": 0.537, "y": 0.789, "value": 1}, {"x": 0.537, "y": 0.838, "value": 1}, {"x": 0.538, "y": 0.824, "value": 1}, {"x": 0.539, "y": 0.822, "value": 1}, {"x": 0.54, "y": 0.819, "value": 1}, {"x": 0.541, "y": 0.899, "value": 1}, {"x": 0.543, "y": 0.796, "value": 1}, {"x": 0.544, "y": 0.828, "value": 1}, {"x": 0.544, "y": 0.917, "value": 1}, {"x": 0.547, "y": 0.775, "value": 1}, {"x": 0.55, "y": 0.839, "value": 1}, {"x": 0.551, "y": 0.827, "value": 1}, {"x": 0.552, "y": 0.802, "value": 1}, {"x": 0.553, "y": 0.78, "value": 1}, {"x": 0.554, "y": 0.821, "value": 1}, {"x": 0.555, "y": 0.778, "value": 1}, {"x": 0.556, "y": 0.863, "value": 1}, {"x": 0.556, "y": 0.9, "value": 1}, {"x": 0.557, "y": 0.86, "value": 1}, {"x": 0.558, "y": 0.844, "value": 1}, {"x": 0.562, "y": 0.8, "value": 1}, {"x": 0.563, "y": 0.836, "value": 1}, {"x": 0.566, "y": 0.772, "value": 1}, {"x": 0.566, "y": 0.785, "value": 1}, {"x": 0.566, "y": 0.796, "value": 1}, {"x": 0.567, "y": 0.841, "value": 1}, {"x": 0.569, "y": 0.814, "value": 1}, {"x": 0.569, "y": 0.836, "value": 1}, {"x": 0.572, "y": 0.846, "value": 1}, {"x": 0.573, "y": 0.88, "value": 1}, {"x": 0.577, "y": 0.769, "value": 1}, {"x": 0.577, "y": 0.846, "value": 1}, {"x": 0.579, "y": 0.908, "value": 1}, {"x": 0.582, "y": 0.832, "value": 1}, {"x": 0.583, "y": 0.895, "value": 1}, {"x": 0.585, "y": 0.858, "value": 1}, {"x": 0.586, "y": 0.768, "value": 1}, {"x": 0.586, "y": 0.836, "value": 1}, {"x": 0.586, "y": 0.866, "value": 1}, {"x": 0.586, "y": 0.906, "value": 1}, {"x": 0.586, "y": 0.908, "value": 1}, {"x": 0.591, "y": 0.841, "value": 1}, {"x": 0.593, "y": 0.928, "value": 1}, {"x": 0.602, "y": 0.961, "value": 1}, {"x": 0.605, "y": 0.783, "value": 1}, {"x": 0.609, "y": 0.769, "value": 1}, {"x": 0.612, "y": 0.897, "value": 1}, {"x": 0.615, "y": 0.847, "value": 1}, {"x": 0.616, "y": 0.827, "value": 1}, {"x": 0.627, "y": 0.78, "value": 1}, {"x": 0.632, "y": 0.872, "value": 1}, {"x": 0.64, "y": 0.777, "value": 1}, {"x": 0.64, "y": 0.817, "value": 1}, {"x": 0.64, "y": 0.889, "value": 1}, {"x": 0.649, "y": 0.793, "value": 1}, {"x": 0.66, "y": 0.913, "value": 1}, {"x": 0.66, "y": 0.871, "value": 1}, {"x": 0.664, "y": 0.791, "value": 1}, {"x": 0.679, "y": 0.803, "value": 1}, {"x": 0.681, "y": 0.814, "value": 1}, {"x": 0.686, "y": 0.888, "value": 1}, {"x": 0.692, "y": 0.81, "value": 1}, {"x": 0.699, "y": 0.927, "value": 1}, {"x": 0.705, "y": 0.807, "value": 1}, {"x": 0.708, "y": 0.924, "value": 1}, {"x": 0.712, "y": 0.808, "value": 1}, {"x": 0.713, "y": 0.919, "value": 1}, {"x": 0.723, "y": 0.941, "value": 1}, {"x": 0.724, "y": 0.956, "value": 1}, {"x": 0.737, "y": 0.941, "value": 1}]